advanced_chunker-0.1.4.dist-info/licenses/LICENSE
semantic_chunker/__init__.py
semantic_chunker/cli.py
semantic_chunker/core.py
semantic_chunker/export.py
semantic_chunker/visualization.py
semantic_chunker/integrations/__init__.py
semantic_chunker/integrations/langchain.py
advanced_chunker-0.1.4.dist-info/METADATA
advanced_chunker-0.1.4.dist-info/WHEEL
advanced_chunker-0.1.4.dist-info/entry_points.txt
advanced_chunker-0.1.4.dist-info/top_level.txt
advanced_chunker-0.1.4.dist-info/RECORD
