Metadata-Version: 2.4
Name: advanced-chunker
Version: 0.1.4
Summary: Semantic-aware chunking and clustering for LLM and RAG pipelines.
Author-email: Rango Ramesh <rango@celestials.ai>
License: MIT
Project-URL: Source, https://github.com/rango-ramesh/semantic-chunking/
Classifier: Programming Language :: Python :: 3
Classifier: License :: OSI Approved :: MIT License
Classifier: Operating System :: OS Independent
Requires-Python: >=3.8
License-File: LICENSE
Requires-Dist: sentence-transformers>=2.2.2
Requires-Dist: scikit-learn
Requires-Dist: matplotlib
Requires-Dist: networkx
Requires-Dist: langchain-core>=0.1.0
Requires-Dist: seaborn
Requires-Dist: langchain
Provides-Extra: dev
Requires-Dist: pytest; extra == "dev"
Requires-Dist: ruff; extra == "dev"
Requires-Dist: build; extra == "dev"
Requires-Dist: twine; extra == "dev"
Dynamic: license-file
